[
    {
        "Marca temporal":1732819158073,
        "¿Tu lugar de residencia es?":null,
        "Si tu lugar de residencia es en Pereira, selecciona la comuna.":null,
        "Por favor, indica tu edad":"35 - 44 años",
        "¿Cuál es tu género? Selecciona una opción:":"Mujer",
        "¿Cuál es tu rango de ingresos mensuales?":"Entre 2 y 3 SMMLV",
        "¿Cuál es tu nivel educativo más alto alcanzado?":"Especialización",
        "¿En qué estrato resides actualmente?":"Estrato 2",
        "¿Sabes cuánto gastas aproximadamente al mes?":"Sí, tengo un cálculo aproximado",
        "¿Qué porcentaje de tus ingresos mensuales destinas para cubrir los siguientes gastos?\n [Deudas y créditos]":"Menos del 10%",
        "¿Qué porcentaje de tus ingresos mensuales destinas para cubrir los siguientes gastos?\n [Alimentación]":"Entre el 10% y el 20%",
        "¿Qué porcentaje de tus ingresos mensuales destinas para cubrir los siguientes gastos?\n [Pagos de servicios domésticos]":"Entre el 10% y el 20%",
        "¿Qué porcentaje de tus ingresos mensuales destinas para cubrir los siguientes gastos?\n [Alquiler de vivienda]":"Entre el 20% y el 40%",
        "¿Qué porcentaje de tus ingresos mensuales destinas para cubrir los siguientes gastos?\n [Transporte]":"Entre el 10% y el 20%",
        "¿Qué porcentaje de tus ingresos mensuales destinas para cubrir los siguientes gastos?\n [Ocio y entretenimiento]":"Entre el 10% y el 20%",
        "¿Tienes alguna deuda activa en este momento? [SI]":"Tarjetas de crédito",
        "En el último año, ¿has intentado reducir tu nivel de endeudamiento?":"Sí, pero no he logrado ahorrar",
        "¿Qué estrategias has utilizado para ahorrar?\n(Puedes seleccionar todas las opciones que apliquen)":"Realizo un presupuesto mensual para controlar mis gastos.",
        "¿Cómo evaluarías tu conocimiento sobre finanzas personales?":"Bueno (Entiendo conceptos importantes)",
        " ¿Te gustaría aprender más sobre manejo financiero?":"Sí",
        "¿Cómo te gustaría aprender a ahorrar?(Selecciona todas las opciones que apliquen) ":"A través de videos educativos en aplicaciones móviles, redes sociales, páginas web, y similares."
    },
    {
        "Marca temporal":1732819878472,
        "¿Tu lugar de residencia es?":"Pereira",
        "Si tu lugar de residencia es en Pereira, selecciona la comuna.":"Comuna Centro",
        "Por favor, indica tu edad":"25 - 34 años",
        "¿Cuál es tu género? Selecciona una opción:":"Mujer",
        "¿Cuál es tu rango de ingresos mensuales?":"Menos de 1 SMMLV (Salario Mínimo Legal Vigente)",
        "¿Cuál es tu nivel educativo más alto alcanzado?":"Pregrado",
        "¿En qué estrato resides actualmente?":"Estrato 5",
        "¿Sabes cuánto gastas aproximadamente al mes?":"Sí, tengo un cálculo aproximado",
        "¿Qué porcentaje de tus ingresos mensuales destinas para cubrir los siguientes gastos?\n [Deudas y créditos]":"Entre el 10% y el 20%",
        "¿Qué porcentaje de tus ingresos mensuales destinas para cubrir los siguientes gastos?\n [Alimentación]":"Entre el 20% y el 40%",
        "¿Qué porcentaje de tus ingresos mensuales destinas para cubrir los siguientes gastos?\n [Pagos de servicios domésticos]":"Entre el 20% y el 40%",
        "¿Qué porcentaje de tus ingresos mensuales destinas para cubrir los siguientes gastos?\n [Alquiler de vivienda]":"Entre el 20% y el 40%",
        "¿Qué porcentaje de tus ingresos mensuales destinas para cubrir los siguientes gastos?\n [Transporte]":"Entre el 20% y el 40%",
        "¿Qué porcentaje de tus ingresos mensuales destinas para cubrir los siguientes gastos?\n [Ocio y entretenimiento]":"Entre el 20% y el 40%",
        "¿Tienes alguna deuda activa en este momento? [SI]":"Créditos de libre inversión",
        "En el último año, ¿has intentado reducir tu nivel de endeudamiento?":"Sí, y he logrado ahorrar",
        "¿Qué estrategias has utilizado para ahorrar?\n(Puedes seleccionar todas las opciones que apliquen)":"Realizo un presupuesto mensual para controlar mis gastos., Aparto un porcentaje fijo de mis ingresos cada mes.",
        "¿Cómo evaluarías tu conocimiento sobre finanzas personales?":"Bueno (Entiendo conceptos importantes)",
        " ¿Te gustaría aprender más sobre manejo financiero?":"Sí",
        "¿Cómo te gustaría aprender a ahorrar?(Selecciona todas las opciones que apliquen) ":"A través de videos educativos en aplicaciones móviles, redes sociales, páginas web, y similares., Mediante juegos o actividades interactivas sobre ahorro."
    },
    {
        "Marca temporal":1732820208503,
        "¿Tu lugar de residencia es?":"Pereira",
        "Si tu lugar de residencia es en Pereira, selecciona la comuna.":"Comuna del Café",
        "Por favor, indica tu edad":"25 - 34 años",
        "¿Cuál es tu género? Selecciona una opción:":"Hombre",
        "¿Cuál es tu rango de ingresos mensuales?":"Entre 2 y 3 SMMLV",
        "¿Cuál es tu nivel educativo más alto alcanzado?":"Maestría",
        "¿En qué estrato resides actualmente?":"Estrato 2",
        "¿Sabes cuánto gastas aproximadamente al mes?":"Sí, tengo un cálculo aproximado",
        "¿Qué porcentaje de tus ingresos mensuales destinas para cubrir los siguientes gastos?\n [Deudas y créditos]":"Menos del 10%",
        "¿Qué porcentaje de tus ingresos mensuales destinas para cubrir los siguientes gastos?\n [Alimentación]":"Entre el 20% y el 40%",
        "¿Qué porcentaje de tus ingresos mensuales destinas para cubrir los siguientes gastos?\n [Pagos de servicios domésticos]":"Entre el 10% y el 20%",
        "¿Qué porcentaje de tus ingresos mensuales destinas para cubrir los siguientes gastos?\n [Alquiler de vivienda]":"Menos del 10%",
        "¿Qué porcentaje de tus ingresos mensuales destinas para cubrir los siguientes gastos?\n [Transporte]":"Entre el 10% y el 20%",
        "¿Qué porcentaje de tus ingresos mensuales destinas para cubrir los siguientes gastos?\n [Ocio y entretenimiento]":"Menos del 10%",
        "¿Tienes alguna deuda activa en este momento? [SI]":"Préstamos de amistades, familiares, etc.",
        "En el último año, ¿has intentado reducir tu nivel de endeudamiento?":"Sí, y he logrado ahorrar",
        "¿Qué estrategias has utilizado para ahorrar?\n(Puedes seleccionar todas las opciones que apliquen)":"Realizo un presupuesto mensual para controlar mis gastos., Reduzco gastos en actividades no esenciales (ocio, entretenimiento, etc.)., No tengo estrategias definidas para ahorrar.",
        "¿Cómo evaluarías tu conocimiento sobre finanzas personales?":"Regular (Puedo tomar decisiones sencillas)",
        " ¿Te gustaría aprender más sobre manejo financiero?":"Sí",
        "¿Cómo te gustaría aprender a ahorrar?(Selecciona todas las opciones que apliquen) ":"A través de videos educativos en aplicaciones móviles, redes sociales, páginas web, y similares., Mediante juegos o actividades interactivas sobre ahorro."
    },
    {
        "Marca temporal":1732820362968,
        "¿Tu lugar de residencia es?":"Pereira",
        "Si tu lugar de residencia es en Pereira, selecciona la comuna.":"Comuna del Café",
        "Por favor, indica tu edad":"25 - 34 años",
        "¿Cuál es tu género? Selecciona una opción:":"Mujer",
        "¿Cuál es tu rango de ingresos mensuales?":"Entre 1 y 2 SMMLV",
        "¿Cuál es tu nivel educativo más alto alcanzado?":"Pregrado",
        "¿En qué estrato resides actualmente?":"Estrato 2",
        "¿Sabes cuánto gastas aproximadamente al mes?":"Sí, tengo un cálculo aproximado",
        "¿Qué porcentaje de tus ingresos mensuales destinas para cubrir los siguientes gastos?\n [Deudas y créditos]":"Entre el 10% y el 20%",
        "¿Qué porcentaje de tus ingresos mensuales destinas para cubrir los siguientes gastos?\n [Alimentación]":"Menos del 10%",
        "¿Qué porcentaje de tus ingresos mensuales destinas para cubrir los siguientes gastos?\n [Pagos de servicios domésticos]":"Menos del 10%",
        "¿Qué porcentaje de tus ingresos mensuales destinas para cubrir los siguientes gastos?\n [Alquiler de vivienda]":"Entre el 10% y el 20%",
        "¿Qué porcentaje de tus ingresos mensuales destinas para cubrir los siguientes gastos?\n [Transporte]":"Menos del 10%",
        "¿Qué porcentaje de tus ingresos mensuales destinas para cubrir los siguientes gastos?\n [Ocio y entretenimiento]":"Entre el 10% y el 20%",
        "¿Tienes alguna deuda activa en este momento? [SI]":"Tarjetas de crédito",
        "En el último año, ¿has intentado reducir tu nivel de endeudamiento?":"Sí, pero no he logrado ahorrar",
        "¿Qué estrategias has utilizado para ahorrar?\n(Puedes seleccionar todas las opciones que apliquen)":"Realizo un presupuesto mensual para controlar mis gastos.",
        "¿Cómo evaluarías tu conocimiento sobre finanzas personales?":"Regular (Puedo tomar decisiones sencillas)",
        " ¿Te gustaría aprender más sobre manejo financiero?":"Sí",
        "¿Cómo te gustaría aprender a ahorrar?(Selecciona todas las opciones que apliquen) ":"Mediante juegos o actividades interactivas sobre ahorro."
    },
    {
        "Marca temporal":1732821560919,
        "¿Tu lugar de residencia es?":"Pereira",
        "Si tu lugar de residencia es en Pereira, selecciona la comuna.":"Comuna El Poblado",
        "Por favor, indica tu edad":"25 - 34 años",
        "¿Cuál es tu género? Selecciona una opción:":"Mujer",
        "¿Cuál es tu rango de ingresos mensuales?":"Entre 2 y 3 SMMLV",
        "¿Cuál es tu nivel educativo más alto alcanzado?":"Pregrado",
        "¿En qué estrato resides actualmente?":"Estrato 3",
        "¿Sabes cuánto gastas aproximadamente al mes?":"Sí, tengo un cálculo aproximado",
        "¿Qué porcentaje de tus ingresos mensuales destinas para cubrir los siguientes gastos?\n [Deudas y créditos]":"Entre el 10% y el 20%",
        "¿Qué porcentaje de tus ingresos mensuales destinas para cubrir los siguientes gastos?\n [Alimentación]":"Entre el 10% y el 20%",
        "¿Qué porcentaje de tus ingresos mensuales destinas para cubrir los siguientes gastos?\n [Pagos de servicios domésticos]":"Menos del 10%",
        "¿Qué porcentaje de tus ingresos mensuales destinas para cubrir los siguientes gastos?\n [Alquiler de vivienda]":"Entre el 20% y el 40%",
        "¿Qué porcentaje de tus ingresos mensuales destinas para cubrir los siguientes gastos?\n [Transporte]":"Menos del 10%",
        "¿Qué porcentaje de tus ingresos mensuales destinas para cubrir los siguientes gastos?\n [Ocio y entretenimiento]":"Menos del 10%",
        "¿Tienes alguna deuda activa en este momento? [SI]":"Crédito educativo",
        "En el último año, ¿has intentado reducir tu nivel de endeudamiento?":"Sí, y he logrado ahorrar",
        "¿Qué estrategias has utilizado para ahorrar?\n(Puedes seleccionar todas las opciones que apliquen)":"Realizo un presupuesto mensual para controlar mis gastos., Aparto un porcentaje fijo de mis ingresos cada mes., Reduzco gastos en actividades no esenciales (ocio, entretenimiento, etc.).",
        "¿Cómo evaluarías tu conocimiento sobre finanzas personales?":"Regular (Puedo tomar decisiones sencillas)",
        " ¿Te gustaría aprender más sobre manejo financiero?":"Sí",
        "¿Cómo te gustaría aprender a ahorrar?(Selecciona todas las opciones que apliquen) ":"A través de videos educativos en aplicaciones móviles, redes sociales, páginas web, y similares., Recibiendo asesorías personalizadas con expertos."
    },
    {
        "Marca temporal":1732823186492,
        "¿Tu lugar de residencia es?":"Pereira",
        "Si tu lugar de residencia es en Pereira, selecciona la comuna.":"Comuna Villa Santana",
        "Por favor, indica tu edad":"25 - 34 años",
        "¿Cuál es tu género? Selecciona una opción:":"Mujer",
        "¿Cuál es tu rango de ingresos mensuales?":"Entre 1 y 2 SMMLV",
        "¿Cuál es tu nivel educativo más alto alcanzado?":"Pregrado",
        "¿En qué estrato resides actualmente?":"Estrato 1",
        "¿Sabes cuánto gastas aproximadamente al mes?":"Sí, tengo un cálculo aproximado",
        "¿Qué porcentaje de tus ingresos mensuales destinas para cubrir los siguientes gastos?\n [Deudas y créditos]":"Menos del 10%",
        "¿Qué porcentaje de tus ingresos mensuales destinas para cubrir los siguientes gastos?\n [Alimentación]":"Entre el 20% y el 40%",
        "¿Qué porcentaje de tus ingresos mensuales destinas para cubrir los siguientes gastos?\n [Pagos de servicios domésticos]":"Entre el 20% y el 40%",
        "¿Qué porcentaje de tus ingresos mensuales destinas para cubrir los siguientes gastos?\n [Alquiler de vivienda]":"Entre el 10% y el 20%",
        "¿Qué porcentaje de tus ingresos mensuales destinas para cubrir los siguientes gastos?\n [Transporte]":"Menos del 10%",
        "¿Qué porcentaje de tus ingresos mensuales destinas para cubrir los siguientes gastos?\n [Ocio y entretenimiento]":"Menos del 10%",
        "¿Tienes alguna deuda activa en este momento? [SI]":"Préstamos de amistades, familiares, etc.",
        "En el último año, ¿has intentado reducir tu nivel de endeudamiento?":"Sí, y he logrado ahorrar",
        "¿Qué estrategias has utilizado para ahorrar?\n(Puedes seleccionar todas las opciones que apliquen)":"Realizo un presupuesto mensual para controlar mis gastos., Aparto un porcentaje fijo de mis ingresos cada mes.",
        "¿Cómo evaluarías tu conocimiento sobre finanzas personales?":"Regular (Puedo tomar decisiones sencillas)",
        " ¿Te gustaría aprender más sobre manejo financiero?":"Sí",
        "¿Cómo te gustaría aprender a ahorrar?(Selecciona todas las opciones que apliquen) ":"Recibiendo asesorías personalizadas con expertos."
    },
    {
        "Marca temporal":1732823461244,
        "¿Tu lugar de residencia es?":"Dosquebradas",
        "Si tu lugar de residencia es en Pereira, selecciona la comuna.":"NO APLICA",
        "Por favor, indica tu edad":"25 - 34 años",
        "¿Cuál es tu género? Selecciona una opción:":"Mujer",
        "¿Cuál es tu rango de ingresos mensuales?":"Menos de 1 SMMLV (Salario Mínimo Legal Vigente)",
        "¿Cuál es tu nivel educativo más alto alcanzado?":"Pregrado",
        "¿En qué estrato resides actualmente?":"Estrato 3",
        "¿Sabes cuánto gastas aproximadamente al mes?":"No, no lo sé con certeza",
        "¿Qué porcentaje de tus ingresos mensuales destinas para cubrir los siguientes gastos?\n [Deudas y créditos]":"Entre el 10% y el 20%",
        "¿Qué porcentaje de tus ingresos mensuales destinas para cubrir los siguientes gastos?\n [Alimentación]":"Entre el 40% y el 50%",
        "¿Qué porcentaje de tus ingresos mensuales destinas para cubrir los siguientes gastos?\n [Pagos de servicios domésticos]":"No aplica",
        "¿Qué porcentaje de tus ingresos mensuales destinas para cubrir los siguientes gastos?\n [Alquiler de vivienda]":"No aplica",
        "¿Qué porcentaje de tus ingresos mensuales destinas para cubrir los siguientes gastos?\n [Transporte]":"Entre el 10% y el 20%",
        "¿Qué porcentaje de tus ingresos mensuales destinas para cubrir los siguientes gastos?\n [Ocio y entretenimiento]":"Entre el 20% y el 40%",
        "¿Tienes alguna deuda activa en este momento? [SI]":"Tarjetas de crédito",
        "En el último año, ¿has intentado reducir tu nivel de endeudamiento?":"Sí, y he logrado ahorrar",
        "¿Qué estrategias has utilizado para ahorrar?\n(Puedes seleccionar todas las opciones que apliquen)":"Utilizo herramientas digitales (aplicaciones bancarias o apps de finanzas).",
        "¿Cómo evaluarías tu conocimiento sobre finanzas personales?":"Bajo (Tengo conocimientos básicos)",
        " ¿Te gustaría aprender más sobre manejo financiero?":"Sí",
        "¿Cómo te gustaría aprender a ahorrar?(Selecciona todas las opciones que apliquen) ":"A través de videos educativos en aplicaciones móviles, redes sociales, páginas web, y similares., Recibiendo asesorías personalizadas con expertos."
    },
    {
        "Marca temporal":1732823483991,
        "¿Tu lugar de residencia es?":"Pereira",
        "Si tu lugar de residencia es en Pereira, selecciona la comuna.":"Comuna Universidad",
        "Por favor, indica tu edad":"25 - 34 años",
        "¿Cuál es tu género? Selecciona una opción:":"Mujer",
        "¿Cuál es tu rango de ingresos mensuales?":"Entre 1 y 2 SMMLV",
        "¿Cuál es tu nivel educativo más alto alcanzado?":"Tecnológico",
        "¿En qué estrato resides actualmente?":"Estrato 2",
        "¿Sabes cuánto gastas aproximadamente al mes?":"No, no lo sé con certeza",
        "¿Qué porcentaje de tus ingresos mensuales destinas para cubrir los siguientes gastos?\n [Deudas y créditos]":"Menos del 10%",
        "¿Qué porcentaje de tus ingresos mensuales destinas para cubrir los siguientes gastos?\n [Alimentación]":"Entre el 20% y el 40%",
        "¿Qué porcentaje de tus ingresos mensuales destinas para cubrir los siguientes gastos?\n [Pagos de servicios domésticos]":"Menos del 10%",
        "¿Qué porcentaje de tus ingresos mensuales destinas para cubrir los siguientes gastos?\n [Alquiler de vivienda]":"Entre el 20% y el 40%",
        "¿Qué porcentaje de tus ingresos mensuales destinas para cubrir los siguientes gastos?\n [Transporte]":"Menos del 10%",
        "¿Qué porcentaje de tus ingresos mensuales destinas para cubrir los siguientes gastos?\n [Ocio y entretenimiento]":"Entre el 20% y el 40%",
        "¿Tienes alguna deuda activa en este momento? [SI]":"No tengo deudas activas",
        "En el último año, ¿has intentado reducir tu nivel de endeudamiento?":"Sí, y he logrado ahorrar",
        "¿Qué estrategias has utilizado para ahorrar?\n(Puedes seleccionar todas las opciones que apliquen)":"No tengo estrategias definidas para ahorrar.",
        "¿Cómo evaluarías tu conocimiento sobre finanzas personales?":"Bajo (Tengo conocimientos básicos)",
        " ¿Te gustaría aprender más sobre manejo financiero?":"Sí",
        "¿Cómo te gustaría aprender a ahorrar?(Selecciona todas las opciones que apliquen) ":"Participando en talleres o cursos presenciales., A través de videos educativos en aplicaciones móviles, redes sociales, páginas web, y similares."
    },
    {
        "Marca temporal":1732826392457,
        "¿Tu lugar de residencia es?":"Pereira",
        "Si tu lugar de residencia es en Pereira, selecciona la comuna.":"Comuna San Nicolás",
        "Por favor, indica tu edad":"25 - 34 años",
        "¿Cuál es tu género? Selecciona una opción:":"Hombre",
        "¿Cuál es tu rango de ingresos mensuales?":"Menos de 1 SMMLV (Salario Mínimo Legal Vigente)",
        "¿Cuál es tu nivel educativo más alto alcanzado?":"Técnico",
        "¿En qué estrato resides actualmente?":"Estrato 3",
        "¿Sabes cuánto gastas aproximadamente al mes?":"No, no lo sé con certeza",
        "¿Qué porcentaje de tus ingresos mensuales destinas para cubrir los siguientes gastos?\n [Deudas y créditos]":"Menos del 10%",
        "¿Qué porcentaje de tus ingresos mensuales destinas para cubrir los siguientes gastos?\n [Alimentación]":"Entre el 10% y el 20%",
        "¿Qué porcentaje de tus ingresos mensuales destinas para cubrir los siguientes gastos?\n [Pagos de servicios domésticos]":"Entre el 10% y el 20%",
        "¿Qué porcentaje de tus ingresos mensuales destinas para cubrir los siguientes gastos?\n [Alquiler de vivienda]":"Entre el 10% y el 20%",
        "¿Qué porcentaje de tus ingresos mensuales destinas para cubrir los siguientes gastos?\n [Transporte]":"Menos del 10%",
        "¿Qué porcentaje de tus ingresos mensuales destinas para cubrir los siguientes gastos?\n [Ocio y entretenimiento]":"Menos del 10%",
        "¿Tienes alguna deuda activa en este momento? [SI]":"Tarjetas de crédito, Crédito educativo, Préstamos de amistades, familiares, etc.",
        "En el último año, ¿has intentado reducir tu nivel de endeudamiento?":"Sí, pero no he logrado ahorrar",
        "¿Qué estrategias has utilizado para ahorrar?\n(Puedes seleccionar todas las opciones que apliquen)":"Realizo un presupuesto mensual para controlar mis gastos., Aparto un porcentaje fijo de mis ingresos cada mes., Compro productos en promoción o al por mayor para ahorrar en compras., No tengo estrategias definidas para ahorrar.",
        "¿Cómo evaluarías tu conocimiento sobre finanzas personales?":"Regular (Puedo tomar decisiones sencillas)",
        " ¿Te gustaría aprender más sobre manejo financiero?":"Sí",
        "¿Cómo te gustaría aprender a ahorrar?(Selecciona todas las opciones que apliquen) ":"A través de videos educativos en aplicaciones móviles, redes sociales, páginas web, y similares., Mediante juegos o actividades interactivas sobre ahorro."
    },
    {
        "Marca temporal":1732826984859,
        "¿Tu lugar de residencia es?":"Pereira",
        "Si tu lugar de residencia es en Pereira, selecciona la comuna.":"Comuna San Nicolás",
        "Por favor, indica tu edad":"45 años o más",
        "¿Cuál es tu género? Selecciona una opción:":"Hombre",
        "¿Cuál es tu rango de ingresos mensuales?":"Menos de 1 SMMLV (Salario Mínimo Legal Vigente)",
        "¿Cuál es tu nivel educativo más alto alcanzado?":"Primaria",
        "¿En qué estrato resides actualmente?":"Estrato 3",
        "¿Sabes cuánto gastas aproximadamente al mes?":"Sí, tengo un cálculo aproximado",
        "¿Qué porcentaje de tus ingresos mensuales destinas para cubrir los siguientes gastos?\n [Deudas y créditos]":"Entre el 10% y el 20%",
        "¿Qué porcentaje de tus ingresos mensuales destinas para cubrir los siguientes gastos?\n [Alimentación]":"Entre el 50% y el 70%",
        "¿Qué porcentaje de tus ingresos mensuales destinas para cubrir los siguientes gastos?\n [Pagos de servicios domésticos]":"Menos del 10%",
        "¿Qué porcentaje de tus ingresos mensuales destinas para cubrir los siguientes gastos?\n [Alquiler de vivienda]":"Menos del 10%",
        "¿Qué porcentaje de tus ingresos mensuales destinas para cubrir los siguientes gastos?\n [Transporte]":"Entre el 50% y el 70%",
        "¿Qué porcentaje de tus ingresos mensuales destinas para cubrir los siguientes gastos?\n [Ocio y entretenimiento]":"Menos del 10%",
        "¿Tienes alguna deuda activa en este momento? [SI]":"Préstamos con gota a gota",
        "En el último año, ¿has intentado reducir tu nivel de endeudamiento?":"Sí, y he logrado ahorrar",
        "¿Qué estrategias has utilizado para ahorrar?\n(Puedes seleccionar todas las opciones que apliquen)":"No tengo estrategias definidas para ahorrar.",
        "¿Cómo evaluarías tu conocimiento sobre finanzas personales?":"Nulo (No tengo conocimientos)",
        " ¿Te gustaría aprender más sobre manejo financiero?":"Sí",
        "¿Cómo te gustaría aprender a ahorrar?(Selecciona todas las opciones que apliquen) ":"Mediante juegos o actividades interactivas sobre ahorro., "
    },
    {
        "Marca temporal":1732827012288,
        "¿Tu lugar de residencia es?":"Pereira",
        "Si tu lugar de residencia es en Pereira, selecciona la comuna.":"Comuna San Nicolás",
        "Por favor, indica tu edad":"45 años o más",
        "¿Cuál es tu género? Selecciona una opción:":"Mujer",
        "¿Cuál es tu rango de ingresos mensuales?":"Entre 2 y 3 SMMLV",
        "¿Cuál es tu nivel educativo más alto alcanzado?":"Tecnológico",
        "¿En qué estrato resides actualmente?":"Estrato 3",
        "¿Sabes cuánto gastas aproximadamente al mes?":"Sí, tengo un cálculo aproximado",
        "¿Qué porcentaje de tus ingresos mensuales destinas para cubrir los siguientes gastos?\n [Deudas y créditos]":"Entre el 10% y el 20%",
        "¿Qué porcentaje de tus ingresos mensuales destinas para cubrir los siguientes gastos?\n [Alimentación]":"Entre el 20% y el 40%",
        "¿Qué porcentaje de tus ingresos mensuales destinas para cubrir los siguientes gastos?\n [Pagos de servicios domésticos]":"Entre el 10% y el 20%",
        "¿Qué porcentaje de tus ingresos mensuales destinas para cubrir los siguientes gastos?\n [Alquiler de vivienda]":"Menos del 10%",
        "¿Qué porcentaje de tus ingresos mensuales destinas para cubrir los siguientes gastos?\n [Transporte]":"Entre el 10% y el 20%",
        "¿Qué porcentaje de tus ingresos mensuales destinas para cubrir los siguientes gastos?\n [Ocio y entretenimiento]":"Menos del 10%",
        "¿Tienes alguna deuda activa en este momento? [SI]":"Tarjetas de crédito, Créditos de libre inversión",
        "En el último año, ¿has intentado reducir tu nivel de endeudamiento?":"Sí, pero no he logrado ahorrar",
        "¿Qué estrategias has utilizado para ahorrar?\n(Puedes seleccionar todas las opciones que apliquen)":"Reduzco gastos en actividades no esenciales (ocio, entretenimiento, etc.)., Compro productos en promoción o al por mayor para ahorrar en compras., Utilizo sistemas informales como “cadenas de ahorro” (natilleras, tandas, etc.).",
        "¿Cómo evaluarías tu conocimiento sobre finanzas personales?":"Bueno (Entiendo conceptos importantes)",
        " ¿Te gustaría aprender más sobre manejo financiero?":"Sí",
        "¿Cómo te gustaría aprender a ahorrar?(Selecciona todas las opciones que apliquen) ":"A través de videos educativos en aplicaciones móviles, redes sociales, páginas web, y similares."
    },
    {
        "Marca temporal":1732829265875,
        "¿Tu lugar de residencia es?":"Pereira",
        "Si tu lugar de residencia es en Pereira, selecciona la comuna.":"Comuna San Nicolás",
        "Por favor, indica tu edad":"45 años o más",
        "¿Cuál es tu género? Selecciona una opción:":"Mujer",
        "¿Cuál es tu rango de ingresos mensuales?":"Más de 4 SMMLV",
        "¿Cuál es tu nivel educativo más alto alcanzado?":"Especialización",
        "¿En qué estrato resides actualmente?":"Estrato 3",
        "¿Sabes cuánto gastas aproximadamente al mes?":"Sí, tengo un cálculo aproximado",
        "¿Qué porcentaje de tus ingresos mensuales destinas para cubrir los siguientes gastos?\n [Deudas y créditos]":"Entre el 20% y el 40%",
        "¿Qué porcentaje de tus ingresos mensuales destinas para cubrir los siguientes gastos?\n [Alimentación]":"Entre el 20% y el 40%",
        "¿Qué porcentaje de tus ingresos mensuales destinas para cubrir los siguientes gastos?\n [Pagos de servicios domésticos]":"Entre el 20% y el 40%",
        "¿Qué porcentaje de tus ingresos mensuales destinas para cubrir los siguientes gastos?\n [Alquiler de vivienda]":"Menos del 10%",
        "¿Qué porcentaje de tus ingresos mensuales destinas para cubrir los siguientes gastos?\n [Transporte]":"Menos del 10%",
        "¿Qué porcentaje de tus ingresos mensuales destinas para cubrir los siguientes gastos?\n [Ocio y entretenimiento]":"Menos del 10%",
        "¿Tienes alguna deuda activa en este momento? [SI]":"Tarjetas de crédito",
        "En el último año, ¿has intentado reducir tu nivel de endeudamiento?":"Sí, pero no he logrado ahorrar",
        "¿Qué estrategias has utilizado para ahorrar?\n(Puedes seleccionar todas las opciones que apliquen)":"Reduzco gastos en actividades no esenciales (ocio, entretenimiento, etc.).",
        "¿Cómo evaluarías tu conocimiento sobre finanzas personales?":"Bueno (Entiendo conceptos importantes)",
        " ¿Te gustaría aprender más sobre manejo financiero?":"Sí",
        "¿Cómo te gustaría aprender a ahorrar?(Selecciona todas las opciones que apliquen) ":"A través de videos educativos en aplicaciones móviles, redes sociales, páginas web, y similares."
    },
    {
        "Marca temporal":1732863809820,
        "¿Tu lugar de residencia es?":"Pereira",
        "Si tu lugar de residencia es en Pereira, selecciona la comuna.":"Comuna Centro",
        "Por favor, indica tu edad":"25 - 34 años",
        "¿Cuál es tu género? Selecciona una opción:":"Mujer",
        "¿Cuál es tu rango de ingresos mensuales?":"Entre 1 y 2 SMMLV",
        "¿Cuál es tu nivel educativo más alto alcanzado?":"Pregrado",
        "¿En qué estrato resides actualmente?":"Estrato 4",
        "¿Sabes cuánto gastas aproximadamente al mes?":"No, no lo sé con certeza",
        "¿Qué porcentaje de tus ingresos mensuales destinas para cubrir los siguientes gastos?\n [Deudas y créditos]":"Menos del 10%",
        "¿Qué porcentaje de tus ingresos mensuales destinas para cubrir los siguientes gastos?\n [Alimentación]":"Entre el 20% y el 40%",
        "¿Qué porcentaje de tus ingresos mensuales destinas para cubrir los siguientes gastos?\n [Pagos de servicios domésticos]":"Entre el 20% y el 40%",
        "¿Qué porcentaje de tus ingresos mensuales destinas para cubrir los siguientes gastos?\n [Alquiler de vivienda]":"Menos del 10%",
        "¿Qué porcentaje de tus ingresos mensuales destinas para cubrir los siguientes gastos?\n [Transporte]":"Entre el 10% y el 20%",
        "¿Qué porcentaje de tus ingresos mensuales destinas para cubrir los siguientes gastos?\n [Ocio y entretenimiento]":"Entre el 10% y el 20%",
        "¿Tienes alguna deuda activa en este momento? [SI]":"No tengo deudas activas",
        "En el último año, ¿has intentado reducir tu nivel de endeudamiento?":"Sí, y he logrado ahorrar",
        "¿Qué estrategias has utilizado para ahorrar?\n(Puedes seleccionar todas las opciones que apliquen)":"Utilizo herramientas digitales (aplicaciones bancarias o apps de finanzas)., Reduzco gastos en actividades no esenciales (ocio, entretenimiento, etc.)., Compro productos en promoción o al por mayor para ahorrar en compras.",
        "¿Cómo evaluarías tu conocimiento sobre finanzas personales?":"Bajo (Tengo conocimientos básicos)",
        " ¿Te gustaría aprender más sobre manejo financiero?":"Sí",
        "¿Cómo te gustaría aprender a ahorrar?(Selecciona todas las opciones que apliquen) ":"Recibiendo asesorías personalizadas con expertos."
    },
    {
        "Marca temporal":1732876908700,
        "¿Tu lugar de residencia es?":"Pereira",
        "Si tu lugar de residencia es en Pereira, selecciona la comuna.":"Comuna San Nicolás",
        "Por favor, indica tu edad":"25 - 34 años",
        "¿Cuál es tu género? Selecciona una opción:":"Mujer",
        "¿Cuál es tu rango de ingresos mensuales?":"Entre 1 y 2 SMMLV",
        "¿Cuál es tu nivel educativo más alto alcanzado?":"Pregrado",
        "¿En qué estrato resides actualmente?":"Estrato 2",
        "¿Sabes cuánto gastas aproximadamente al mes?":"Sí, tengo un cálculo aproximado",
        "¿Qué porcentaje de tus ingresos mensuales destinas para cubrir los siguientes gastos?\n [Deudas y créditos]":"Entre el 40% y el 50%",
        "¿Qué porcentaje de tus ingresos mensuales destinas para cubrir los siguientes gastos?\n [Alimentación]":"Menos del 10%",
        "¿Qué porcentaje de tus ingresos mensuales destinas para cubrir los siguientes gastos?\n [Pagos de servicios domésticos]":"Entre el 20% y el 40%",
        "¿Qué porcentaje de tus ingresos mensuales destinas para cubrir los siguientes gastos?\n [Alquiler de vivienda]":"Menos del 10%",
        "¿Qué porcentaje de tus ingresos mensuales destinas para cubrir los siguientes gastos?\n [Transporte]":"Menos del 10%",
        "¿Qué porcentaje de tus ingresos mensuales destinas para cubrir los siguientes gastos?\n [Ocio y entretenimiento]":"Menos del 10%",
        "¿Tienes alguna deuda activa en este momento? [SI]":"Tarjetas de crédito, Créditos de libre inversión, Crédito educativo",
        "En el último año, ¿has intentado reducir tu nivel de endeudamiento?":"Sí, pero no he logrado ahorrar",
        "¿Qué estrategias has utilizado para ahorrar?\n(Puedes seleccionar todas las opciones que apliquen)":"Realizo un presupuesto mensual para controlar mis gastos.",
        "¿Cómo evaluarías tu conocimiento sobre finanzas personales?":"Regular (Puedo tomar decisiones sencillas)",
        " ¿Te gustaría aprender más sobre manejo financiero?":"Sí",
        "¿Cómo te gustaría aprender a ahorrar?(Selecciona todas las opciones que apliquen) ":"A través de videos educativos en aplicaciones móviles, redes sociales, páginas web, y similares."
    },
    {
        "Marca temporal":1732879146261,
        "¿Tu lugar de residencia es?":"Pereira",
        "Si tu lugar de residencia es en Pereira, selecciona la comuna.":"Comuna San Joaquín",
        "Por favor, indica tu edad":"25 - 34 años",
        "¿Cuál es tu género? Selecciona una opción:":"Hombre",
        "¿Cuál es tu rango de ingresos mensuales?":"Más de 4 SMMLV",
        "¿Cuál es tu nivel educativo más alto alcanzado?":"Especialización",
        "¿En qué estrato resides actualmente?":"Estrato 3",
        "¿Sabes cuánto gastas aproximadamente al mes?":"Sí, tengo un cálculo aproximado",
        "¿Qué porcentaje de tus ingresos mensuales destinas para cubrir los siguientes gastos?\n [Deudas y créditos]":"Entre el 10% y el 20%",
        "¿Qué porcentaje de tus ingresos mensuales destinas para cubrir los siguientes gastos?\n [Alimentación]":"Entre el 10% y el 20%",
        "¿Qué porcentaje de tus ingresos mensuales destinas para cubrir los siguientes gastos?\n [Pagos de servicios domésticos]":"Entre el 10% y el 20%",
        "¿Qué porcentaje de tus ingresos mensuales destinas para cubrir los siguientes gastos?\n [Alquiler de vivienda]":"Entre el 10% y el 20%",
        "¿Qué porcentaje de tus ingresos mensuales destinas para cubrir los siguientes gastos?\n [Transporte]":"Entre el 10% y el 20%",
        "¿Qué porcentaje de tus ingresos mensuales destinas para cubrir los siguientes gastos?\n [Ocio y entretenimiento]":"Entre el 10% y el 20%",
        "¿Tienes alguna deuda activa en este momento? [SI]":"Créditos de vivienda o vehículo",
        "En el último año, ¿has intentado reducir tu nivel de endeudamiento?":"Sí, y he logrado ahorrar",
        "¿Qué estrategias has utilizado para ahorrar?\n(Puedes seleccionar todas las opciones que apliquen)":"Realizo un presupuesto mensual para controlar mis gastos., Utilizo herramientas digitales (aplicaciones bancarias o apps de finanzas)., Reduzco gastos en actividades no esenciales (ocio, entretenimiento, etc.)., Invierto en productos financieros (CDTs, fondos de inversión, etc.).",
        "¿Cómo evaluarías tu conocimiento sobre finanzas personales?":"Excelente (Manejo muy bien mis finanzas)",
        " ¿Te gustaría aprender más sobre manejo financiero?":"Sí",
        "¿Cómo te gustaría aprender a ahorrar?(Selecciona todas las opciones que apliquen) ":"Participando en talleres o cursos presenciales., A través de videos educativos en aplicaciones móviles, redes sociales, páginas web, y similares."
    },
    {
        "Marca temporal":1732883183364,
        "¿Tu lugar de residencia es?":"Pereira",
        "Si tu lugar de residencia es en Pereira, selecciona la comuna.":"Comuna Oriente",
        "Por favor, indica tu edad":"25 - 34 años",
        "¿Cuál es tu género? Selecciona una opción:":"Hombre",
        "¿Cuál es tu rango de ingresos mensuales?":"Entre 1 y 2 SMMLV",
        "¿Cuál es tu nivel educativo más alto alcanzado?":"Técnico",
        "¿En qué estrato resides actualmente?":"Estrato 3",
        "¿Sabes cuánto gastas aproximadamente al mes?":"Sí, tengo un cálculo aproximado",
        "¿Qué porcentaje de tus ingresos mensuales destinas para cubrir los siguientes gastos?\n [Deudas y créditos]":"Entre el 50% y el 70%",
        "¿Qué porcentaje de tus ingresos mensuales destinas para cubrir los siguientes gastos?\n [Alimentación]":"Menos del 10%",
        "¿Qué porcentaje de tus ingresos mensuales destinas para cubrir los siguientes gastos?\n [Pagos de servicios domésticos]":"Entre el 10% y el 20%",
        "¿Qué porcentaje de tus ingresos mensuales destinas para cubrir los siguientes gastos?\n [Alquiler de vivienda]":"No aplica",
        "¿Qué porcentaje de tus ingresos mensuales destinas para cubrir los siguientes gastos?\n [Transporte]":"Menos del 10%",
        "¿Qué porcentaje de tus ingresos mensuales destinas para cubrir los siguientes gastos?\n [Ocio y entretenimiento]":"Entre el 10% y el 20%",
        "¿Tienes alguna deuda activa en este momento? [SI]":"Tarjetas de crédito, Préstamos de amistades, familiares, etc.",
        "En el último año, ¿has intentado reducir tu nivel de endeudamiento?":"Sí, pero no he logrado ahorrar",
        "¿Qué estrategias has utilizado para ahorrar?\n(Puedes seleccionar todas las opciones que apliquen)":"No tengo estrategias definidas para ahorrar.",
        "¿Cómo evaluarías tu conocimiento sobre finanzas personales?":"Bajo (Tengo conocimientos básicos)",
        " ¿Te gustaría aprender más sobre manejo financiero?":"Sí",
        "¿Cómo te gustaría aprender a ahorrar?(Selecciona todas las opciones que apliquen) ":"Participando en talleres o cursos presenciales., Recibiendo asesorías personalizadas con expertos., Mediante juegos o actividades interactivas sobre ahorro."
    },
    {
        "Marca temporal":1732887928698,
        "¿Tu lugar de residencia es?":"Pereira",
        "Si tu lugar de residencia es en Pereira, selecciona la comuna.":"Comuna San Joaquín",
        "Por favor, indica tu edad":"35 - 44 años",
        "¿Cuál es tu género? Selecciona una opción:":"Mujer",
        "¿Cuál es tu rango de ingresos mensuales?":"Entre 1 y 2 SMMLV",
        "¿Cuál es tu nivel educativo más alto alcanzado?":"Técnico",
        "¿En qué estrato resides actualmente?":"Estrato 2",
        "¿Sabes cuánto gastas aproximadamente al mes?":"Sí, tengo un cálculo aproximado",
        "¿Qué porcentaje de tus ingresos mensuales destinas para cubrir los siguientes gastos?\n [Deudas y créditos]":"Entre el 20% y el 40%",
        "¿Qué porcentaje de tus ingresos mensuales destinas para cubrir los siguientes gastos?\n [Alimentación]":"Entre el 10% y el 20%",
        "¿Qué porcentaje de tus ingresos mensuales destinas para cubrir los siguientes gastos?\n [Pagos de servicios domésticos]":"Menos del 10%",
        "¿Qué porcentaje de tus ingresos mensuales destinas para cubrir los siguientes gastos?\n [Alquiler de vivienda]":"Menos del 10%",
        "¿Qué porcentaje de tus ingresos mensuales destinas para cubrir los siguientes gastos?\n [Transporte]":"Menos del 10%",
        "¿Qué porcentaje de tus ingresos mensuales destinas para cubrir los siguientes gastos?\n [Ocio y entretenimiento]":"Menos del 10%",
        "¿Tienes alguna deuda activa en este momento? [SI]":"Créditos de libre inversión",
        "En el último año, ¿has intentado reducir tu nivel de endeudamiento?":"Sí, y he logrado ahorrar",
        "¿Qué estrategias has utilizado para ahorrar?\n(Puedes seleccionar todas las opciones que apliquen)":"Realizo un presupuesto mensual para controlar mis gastos., Aparto un porcentaje fijo de mis ingresos cada mes., Reduzco gastos en actividades no esenciales (ocio, entretenimiento, etc.).",
        "¿Cómo evaluarías tu conocimiento sobre finanzas personales?":"Bueno (Entiendo conceptos importantes)",
        " ¿Te gustaría aprender más sobre manejo financiero?":"No",
        "¿Cómo te gustaría aprender a ahorrar?(Selecciona todas las opciones que apliquen) ":null
    },
    {
        "Marca temporal":1732890592347,
        "¿Tu lugar de residencia es?":"Dosquebradas",
        "Si tu lugar de residencia es en Pereira, selecciona la comuna.":"NO APLICA",
        "Por favor, indica tu edad":"18 - 24 años",
        "¿Cuál es tu género? Selecciona una opción:":"Hombre",
        "¿Cuál es tu rango de ingresos mensuales?":"Menos de 1 SMMLV (Salario Mínimo Legal Vigente)",
        "¿Cuál es tu nivel educativo más alto alcanzado?":"Técnico",
        "¿En qué estrato resides actualmente?":"Estrato 2",
        "¿Sabes cuánto gastas aproximadamente al mes?":"No, no lo sé con certeza",
        "¿Qué porcentaje de tus ingresos mensuales destinas para cubrir los siguientes gastos?\n [Deudas y créditos]":"Entre el 20% y el 40%",
        "¿Qué porcentaje de tus ingresos mensuales destinas para cubrir los siguientes gastos?\n [Alimentación]":"Menos del 10%",
        "¿Qué porcentaje de tus ingresos mensuales destinas para cubrir los siguientes gastos?\n [Pagos de servicios domésticos]":"Menos del 10%",
        "¿Qué porcentaje de tus ingresos mensuales destinas para cubrir los siguientes gastos?\n [Alquiler de vivienda]":"Menos del 10%",
        "¿Qué porcentaje de tus ingresos mensuales destinas para cubrir los siguientes gastos?\n [Transporte]":"Entre el 20% y el 40%",
        "¿Qué porcentaje de tus ingresos mensuales destinas para cubrir los siguientes gastos?\n [Ocio y entretenimiento]":"Entre el 20% y el 40%",
        "¿Tienes alguna deuda activa en este momento? [SI]":"No tengo deudas activas",
        "En el último año, ¿has intentado reducir tu nivel de endeudamiento?":"Sí, y he logrado ahorrar",
        "¿Qué estrategias has utilizado para ahorrar?\n(Puedes seleccionar todas las opciones que apliquen)":"Aparto un porcentaje fijo de mis ingresos cada mes., Reduzco gastos en actividades no esenciales (ocio, entretenimiento, etc.)., Compro productos en promoción o al por mayor para ahorrar en compras.",
        "¿Cómo evaluarías tu conocimiento sobre finanzas personales?":"Regular (Puedo tomar decisiones sencillas)",
        " ¿Te gustaría aprender más sobre manejo financiero?":"Sí",
        "¿Cómo te gustaría aprender a ahorrar?(Selecciona todas las opciones que apliquen) ":"Participando en talleres o cursos presenciales., A través de videos educativos en aplicaciones móviles, redes sociales, páginas web, y similares., Mediante juegos o actividades interactivas sobre ahorro."
    },
    {
        "Marca temporal":1732892469310,
        "¿Tu lugar de residencia es?":"Otro municipio de Risaralda",
        "Si tu lugar de residencia es en Pereira, selecciona la comuna.":"NO APLICA",
        "Por favor, indica tu edad":"25 - 34 años",
        "¿Cuál es tu género? Selecciona una opción:":"Mujer",
        "¿Cuál es tu rango de ingresos mensuales?":"Entre 1 y 2 SMMLV",
        "¿Cuál es tu nivel educativo más alto alcanzado?":"Pregrado",
        "¿En qué estrato resides actualmente?":"Estrato 3",
        "¿Sabes cuánto gastas aproximadamente al mes?":"No, no lo sé con certeza",
        "¿Qué porcentaje de tus ingresos mensuales destinas para cubrir los siguientes gastos?\n [Deudas y créditos]":"Entre el 10% y el 20%",
        "¿Qué porcentaje de tus ingresos mensuales destinas para cubrir los siguientes gastos?\n [Alimentación]":"Entre el 10% y el 20%",
        "¿Qué porcentaje de tus ingresos mensuales destinas para cubrir los siguientes gastos?\n [Pagos de servicios domésticos]":"Entre el 10% y el 20%",
        "¿Qué porcentaje de tus ingresos mensuales destinas para cubrir los siguientes gastos?\n [Alquiler de vivienda]":"Menos del 10%",
        "¿Qué porcentaje de tus ingresos mensuales destinas para cubrir los siguientes gastos?\n [Transporte]":"Menos del 10%",
        "¿Qué porcentaje de tus ingresos mensuales destinas para cubrir los siguientes gastos?\n [Ocio y entretenimiento]":"Entre el 10% y el 20%",
        "¿Tienes alguna deuda activa en este momento? [SI]":"Créditos de vivienda o vehículo",
        "En el último año, ¿has intentado reducir tu nivel de endeudamiento?":"Sí, pero no he logrado ahorrar",
        "¿Qué estrategias has utilizado para ahorrar?\n(Puedes seleccionar todas las opciones que apliquen)":"No tengo estrategias definidas para ahorrar.",
        "¿Cómo evaluarías tu conocimiento sobre finanzas personales?":"Bajo (Tengo conocimientos básicos)",
        " ¿Te gustaría aprender más sobre manejo financiero?":"Sí",
        "¿Cómo te gustaría aprender a ahorrar?(Selecciona todas las opciones que apliquen) ":"A través de videos educativos en aplicaciones móviles, redes sociales, páginas web, y similares."
    },
    {
        "Marca temporal":1732963873530,
        "¿Tu lugar de residencia es?":"Dosquebradas",
        "Si tu lugar de residencia es en Pereira, selecciona la comuna.":"NO APLICA",
        "Por favor, indica tu edad":"18 - 24 años",
        "¿Cuál es tu género? Selecciona una opción:":"Hombre",
        "¿Cuál es tu rango de ingresos mensuales?":"Menos de 1 SMMLV (Salario Mínimo Legal Vigente)",
        "¿Cuál es tu nivel educativo más alto alcanzado?":"Técnico",
        "¿En qué estrato resides actualmente?":"Estrato 2",
        "¿Sabes cuánto gastas aproximadamente al mes?":"Sí, tengo un cálculo aproximado",
        "¿Qué porcentaje de tus ingresos mensuales destinas para cubrir los siguientes gastos?\n [Deudas y créditos]":"Menos del 10%",
        "¿Qué porcentaje de tus ingresos mensuales destinas para cubrir los siguientes gastos?\n [Alimentación]":"Entre el 50% y el 70%",
        "¿Qué porcentaje de tus ingresos mensuales destinas para cubrir los siguientes gastos?\n [Pagos de servicios domésticos]":"Entre el 10% y el 20%",
        "¿Qué porcentaje de tus ingresos mensuales destinas para cubrir los siguientes gastos?\n [Alquiler de vivienda]":"No aplica",
        "¿Qué porcentaje de tus ingresos mensuales destinas para cubrir los siguientes gastos?\n [Transporte]":"Entre el 10% y el 20%",
        "¿Qué porcentaje de tus ingresos mensuales destinas para cubrir los siguientes gastos?\n [Ocio y entretenimiento]":"Menos del 10%",
        "¿Tienes alguna deuda activa en este momento? [SI]":"Tarjetas de crédito",
        "En el último año, ¿has intentado reducir tu nivel de endeudamiento?":"Sí, y he logrado ahorrar",
        "¿Qué estrategias has utilizado para ahorrar?\n(Puedes seleccionar todas las opciones que apliquen)":"Realizo un presupuesto mensual para controlar mis gastos., Compro productos en promoción o al por mayor para ahorrar en compras.",
        "¿Cómo evaluarías tu conocimiento sobre finanzas personales?":"Regular (Puedo tomar decisiones sencillas)",
        " ¿Te gustaría aprender más sobre manejo financiero?":"Sí",
        "¿Cómo te gustaría aprender a ahorrar?(Selecciona todas las opciones que apliquen) ":"Mediante juegos o actividades interactivas sobre ahorro."
    },
    {
        "Marca temporal":1733046441555,
        "¿Tu lugar de residencia es?":"Pereira",
        "Si tu lugar de residencia es en Pereira, selecciona la comuna.":"Comuna San Nicolás",
        "Por favor, indica tu edad":"18 - 24 años",
        "¿Cuál es tu género? Selecciona una opción:":"Mujer",
        "¿Cuál es tu rango de ingresos mensuales?":"Entre 1 y 2 SMMLV",
        "¿Cuál es tu nivel educativo más alto alcanzado?":"Pregrado",
        "¿En qué estrato resides actualmente?":"Estrato 3",
        "¿Sabes cuánto gastas aproximadamente al mes?":"Sí, tengo un cálculo aproximado",
        "¿Qué porcentaje de tus ingresos mensuales destinas para cubrir los siguientes gastos?\n [Deudas y créditos]":"Entre el 50% y el 70%",
        "¿Qué porcentaje de tus ingresos mensuales destinas para cubrir los siguientes gastos?\n [Alimentación]":"Entre el 10% y el 20%",
        "¿Qué porcentaje de tus ingresos mensuales destinas para cubrir los siguientes gastos?\n [Pagos de servicios domésticos]":"Menos del 10%",
        "¿Qué porcentaje de tus ingresos mensuales destinas para cubrir los siguientes gastos?\n [Alquiler de vivienda]":"No aplica",
        "¿Qué porcentaje de tus ingresos mensuales destinas para cubrir los siguientes gastos?\n [Transporte]":"Entre el 10% y el 20%",
        "¿Qué porcentaje de tus ingresos mensuales destinas para cubrir los siguientes gastos?\n [Ocio y entretenimiento]":"Menos del 10%",
        "¿Tienes alguna deuda activa en este momento? [SI]":"Tarjetas de crédito, Créditos de vivienda o vehículo",
        "En el último año, ¿has intentado reducir tu nivel de endeudamiento?":"No he reducido mi nivel de endeudamiento",
        "¿Qué estrategias has utilizado para ahorrar?\n(Puedes seleccionar todas las opciones que apliquen)":"Realizo un presupuesto mensual para controlar mis gastos., Utilizo herramientas digitales (aplicaciones bancarias o apps de finanzas).",
        "¿Cómo evaluarías tu conocimiento sobre finanzas personales?":"Regular (Puedo tomar decisiones sencillas)",
        " ¿Te gustaría aprender más sobre manejo financiero?":"Sí",
        "¿Cómo te gustaría aprender a ahorrar?(Selecciona todas las opciones que apliquen) ":"A través de videos educativos en aplicaciones móviles, redes sociales, páginas web, y similares., Recibiendo asesorías personalizadas con expertos., Mediante juegos o actividades interactivas sobre ahorro."
    }
]